classy_fastapi/__init__.py
classy_fastapi/decorators.py
classy_fastapi/py.typed
classy_fastapi/routable.py
classy_fastapi/route_args.py
classy_fastapi/test_routable.py
classy_fastapi-0.7.0.dist-info/METADATA
classy_fastapi-0.7.0.dist-info/WHEEL
classy_fastapi-0.7.0.dist-info/licenses/LICENSE.txt
classy_fastapi-0.7.0.dist-info/RECORD
