Metadata-Version: 2.4
Name: classy-fastapi
Version: 0.7.0
Summary: Class based routing for FastAPI
License: MIT
License-File: LICENSE.txt
Keywords: FastAPI,Class,Instance,Routing
Author: Oliver Dain
Author-email: oliver@dains.org
Requires-Python: >=3.9
Classifier: License :: OSI Approved :: MIT License
Classifier: Programming Language :: Python :: 3
Classifier: Programming Language :: Python :: 3.9
Classifier: Programming Language :: Python :: 3.10
Classifier: Programming Language :: Python :: 3.11
Classifier: Programming Language :: Python :: 3.12
Classifier: Programming Language :: Python :: 3.13
Classifier: Programming Language :: Python :: 3.14
Requires-Dist: fastapi (>=0.73.0,<1.0.0)
Requires-Dist: pydantic (>=2.8,<3.0.0)
Project-URL: Homepage, https://gitlab.com/companionlabs-opensource/classy-fastapi
Project-URL: Repository, https://gitlab.com/companionlabs-opensource/classy-fastapi
